cywhispercpp/__about__.py
cywhispercpp/__init__.py
cywhispercpp/core.py
cywhispercpp/utils.py
cywhispercpp/resources/PLACE_YOUR_FILES_HERE
cywhispercpp-0.0.1.dist-info/METADATA
cywhispercpp-0.0.1.dist-info/WHEEL
cywhispercpp-0.0.1.dist-info/licenses/LICENSE.txt
cywhispercpp-0.0.1.dist-info/RECORD
