Metadata-Version: 2.4
Name: cywhispercpp
Version: 0.0.1
Project-URL: Source, https://github.com/mohammadraziei/cywhispercpp
Project-URL: Issues, https://github.com/mohammadraziei/cywhispercpp/issues
Project-URL: Documentation, https://mohammadraziei.github.io/cywhispercpp
Author-email: Mohammad Raziei <mohammadraziei1375@gmail.com>
License-Expression: MIT
License-File: LICENSE.txt
Classifier: Development Status :: 4 - Beta
Classifier: License :: OSI Approved :: MIT License
Classifier: Operating System :: OS Independent
Classifier: Programming Language :: Python
Classifier: Programming Language :: Python :: 3 :: Only
Classifier: Programming Language :: Python :: 3.7
Classifier: Programming Language :: Python :: 3.8
Classifier: Programming Language :: Python :: 3.9
Classifier: Programming Language :: Python :: 3.10
Classifier: Programming Language :: Python :: 3.11
Classifier: Programming Language :: Python :: 3.12
Classifier: Programming Language :: Python :: 3.13
Classifier: Programming Language :: Python :: Implementation :: CPython
Classifier: Programming Language :: Python :: Implementation :: PyPy
Requires-Python: >=3.7
Requires-Dist: numpy
